 {
  "TargetList": [
    {
      "Name": "MainEntrance",
      "FloorNumber": 4,
      "Position": {
        "x": 80.86,
        "y": 1,
        "z": 3.9
      },
      "Rotation": {
        "x": 0,
        "y": 0,
        "z": 0
      }
    },
    {
      "Name": "Lab",
      "FloorNumber": 4,
      "Position": {
        "x": 20,
        "y": 1,
        "z": -8
      },
      "Rotation": {
        "x": 0,
        "y": 0,
        "z": 0
      }
    },
    {
      "Name": "Elevator",
      "FloorNumber": 4,
      "Position": {
        "x": 33,
        "y": 1,
        "z": -8
      },
      "Rotation": {
        "x": 0,
        "y": 0,
        "z": 0
      }
    },
    {
      "Name": "C408",
      "FloorNumber": 4,
      "Position": {
        "x": 73.3,
        "y": 1,
        "z": -7.6
      },
      "Rotation": {
        "x": 0,
        "y": 0,
        "z": 0
      }
    },
    {
      "Name": "C406",
      "FloorNumber": 4,
      "Position": {
        "x": 66.9,
        "y": 1,
        "z": -7.6
      },
      "Rotation": {
        "x": 0,
        "y": 0,
        "z": 0
      }
    },
    {
      "Name": "C405",
      "FloorNumber": 4,
      "Position": {
        "x": 60.1,
        "y": 1,
        "z": -7.5
      },
      "Rotation": {
        "x": 0,
        "y": -90,
        "z": 0
      }
    },
    {
      "Name": "C404",
      "FloorNumber": 4,
      "Position": {
        "x": 53.4,
        "y": 1,
        "z": -7.6
      },
      "Rotation": {
        "x": 0,
        "y": 0,
        "z": 0
      }
    },
    {
      "Name": "C403",
      "FloorNumber": 4,
      "Position": {
        "x": 46.8,
        "y": 1,
        "z": -7.7
      },
      "Rotation": {
        "x": 0,
        "y": 180,
        "z": 0
      }
    },
    {
      "Name": "LastRoom",
      "FloorNumber": 4,
      "Position": {
        "x": 1.190002,
        "y": 1,
        "z": -1.99
      },
      "Rotation": {
        "x": 0,
        "y": 0,
        "z": 0
      }
    },
        {
      "Name": "MainEntrance",
      "FloorNumber": 3,
      "Position": {
        "x": 80.86,
        "y": 1,
        "z": -26
      },
      "Rotation": {
        "x": 0,
        "y": 0,
        "z": 0
      }
    },
    {
      "Name": "Lab",
      "FloorNumber": 3,
      "Position": {
        "x": 20,
        "y": 1,
        "z": -38
      },
      "Rotation": {
        "x": 0,
        "y": 0,
        "z": 0
      }
    },
    {
      "Name": "3-Elevator",
      "FloorNumber": 3,
      "Position": {
        "x": 33,
        "y": 1,
        "z": -38
      },
      "Rotation": {
        "x": 0,
        "y": 0,
        "z": 0
      }
    },
    {
      "Name": "C308",
      "FloorNumber": 3,
      "Position": {
        "x": 73.3,
        "y": 1,
        "z": -37.6
      },
      "Rotation": {
        "x": 0,
        "y": 0,
        "z": 0
      }
    },
    {
      "Name": "C306",
      "FloorNumber": 3,
      "Position": {
        "x": 66.9,
        "y": 1,
        "z": -37.6
      },
      "Rotation": {
        "x": 0,
        "y": 0,
        "z": 0
      }
    },
    {
      "Name": "C305",
      "FloorNumber": 3,
      "Position": {
        "x": 60.1,
        "y": 1,
        "z": -37.5
      },
      "Rotation": {
        "x": 0,
        "y": -90,
        "z": 0
      }
    },
    {
      "Name": "C304",
      "FloorNumber": 3,
      "Position": {
        "x": 53.4,
        "y": 1,
        "z": -37.6
      },
      "Rotation": {
        "x": 0,
        "y": 0,
        "z": 0
      }
    },
    {
      "Name": "C303",
      "FloorNumber": 3,
      "Position": {
        "x": 46.8,
        "y": 1,
        "z": -37.7
      },
      "Rotation": {
        "x": 0,
        "y": 180,
        "z": 0
      }
    },
    {
      "Name": "LastRoom",
      "FloorNumber": 3,
      "Position": {
        "x": 1.190002,
        "y": 1,
        "z": -31.99
      },
      "Rotation": {
        "x": 0,
        "y": 0,
        "z": 0
      }
    }
  ]
}